todo/__init__.py
todo/main.py
todo/models.py
todo/storage.py
todo/commands/__init__.py
todo/commands/add.py
todo/commands/complete.py
todo/commands/delete.py
todo/commands/edit.py
todo/commands/init.py
todo/commands/list.py
todo/commands/show.py
todo_oio-0.1.0.dist-info/METADATA
todo_oio-0.1.0.dist-info/WHEEL
todo_oio-0.1.0.dist-info/entry_points.txt
todo_oio-0.1.0.dist-info/licenses/LICENSE
todo_oio-0.1.0.dist-info/RECORD
