Metadata-Version: 2.4
Name: todo-oio
Version: 0.1.0
Summary: A modern, intuitive CLI todo application with beautiful terminal UI
Project-URL: Homepage, https://github.com/todo-oio/todo-oio
Project-URL: Repository, https://github.com/todo-oio/todo-oio
Project-URL: Issues, https://github.com/todo-oio/todo-oio/issues
Project-URL: Documentation, https://github.com/todo-oio/todo-oio#readme
Project-URL: Changelog, https://github.com/todo-oio/todo-oio/releases
Author-email: Todo OIO Team <contact@todo-oio.dev>
License: MIT
License-File: LICENSE
Keywords: cli,modern,productivity,task-management,terminal,todo
Classifier: Development Status :: 4 - Beta
Classifier: Environment :: Console
Classifier: Intended Audience :: Developers
Classifier: Intended Audience :: End Users/Desktop
Classifier: License :: OSI Approved :: MIT License
Classifier: Operating System :: OS Independent
Classifier: Programming Language :: Python :: 3
Classifier: Programming Language :: Python :: 3.8
Classifier: Programming Language :: Python :: 3.9
Classifier: Programming Language :: Python :: 3.10
Classifier: Programming Language :: Python :: 3.11
Classifier: Programming Language :: Python :: 3.12
Classifier: Topic :: Office/Business :: Scheduling
Classifier: Topic :: Software Development :: Libraries :: Application Frameworks
Classifier: Topic :: System :: Shells
Classifier: Topic :: Terminals
Classifier: Topic :: Utilities
Classifier: Typing :: Typed
Requires-Python: >=3.8
Requires-Dist: click>=8.0.0
Requires-Dist: rich>=13.0.0
Requires-Dist: typer[all]>=0.9.0
Provides-Extra: dev
Requires-Dist: black>=23.0.0; extra == 'dev'
Requires-Dist: flake8>=6.0.0; extra == 'dev'
Requires-Dist: isort>=5.0.0; extra == 'dev'
Requires-Dist: mypy>=1.0.0; extra == 'dev'
Requires-Dist: pytest-cov>=4.0.0; extra == 'dev'
Requires-Dist: pytest>=7.0.0; extra == 'dev'
